cody_cli/__init__.py
cody_cli/cli.py
cody_cli-0.1.1.dist-info/METADATA
cody_cli-0.1.1.dist-info/WHEEL
cody_cli-0.1.1.dist-info/entry_points.txt
cody_cli-0.1.1.dist-info/RECORD
