Metadata-Version: 2.1
Name: cody-cli
Version: 0.1.1
Summary: 
Author: xangcastle
Author-email: xangcastle@gmail.com
Requires-Python: >=3.8,<4.0
Classifier: Programming Language :: Python :: 3
Classifier: Programming Language :: Python :: 3.8
Classifier: Programming Language :: Python :: 3.9
Classifier: Programming Language :: Python :: 3.10
Classifier: Programming Language :: Python :: 3.11
Classifier: Programming Language :: Python :: 3.12
Requires-Dist: click (>=8.1.7,<9.0.0)
Requires-Dist: openai (>=1.7.2,<2.0.0)
Requires-Dist: requests (>=2.31.0,<3.0.0)
